COPYING.txt
MANIFEST.in
README.md
setup.cfg
setup.py
gsvloader/__init__.py
gsvloader/loader.py
gsvloader/polygon_to_points.py
gsvloader.egg-info/PKG-INFO
gsvloader.egg-info/SOURCES.txt
gsvloader.egg-info/dependency_links.txt
gsvloader.egg-info/top_level.txt