Metadata-Version: 1.0
Name: gsvloader
Version: 0.1.5
Summary: Google Street View Retrieval
Home-page: https://github.com/pcrete
Author: Poom Wettayakorn
Author-email: poom.wettayakorn@gmail.com
License: UNKNOWN
Platform: UNKNOWN
